{"minecraft:recipes/decorations/torch":{"criteria":{"has_stone_pickaxe":"2025-08-11 12:28:59 +0000"},"done":true},"minecraft:story/upgrade_tools":{"criteria":{"stone_pickaxe":"2025-08-11 12:28:59 +0000"},"done":true},"minecraft:recipes/decorations/crafting_table":{"criteria":{"unlock_right_away":"2025-08-11 12:28:59 +0000"},"done":true},"minecraft:adventure/adventuring_time":{"criteria":{"minecraft:frozen_river":"2025-08-11 12:36:57 +0000","minecraft:snowy_plains":"2025-08-11 12:29:00 +0000","minecraft:snowy_taiga":"2025-08-11 13:55:59 +0000","minecraft:snowy_beach":"2025-08-13 12:25:13 +0000"},"done":false},"minecraft:recipes/decorations/green_bed":{"criteria":{"has_green_wool":"2025-08-11 12:48:27 +0000"},"done":true},"minecraft:recipes/decorations/green_banner":{"criteria":{"has_green_wool":"2025-08-11 12:48:27 +0000"},"done":true},"minecraft:recipes/decorations/painting":{"criteria":{"has_wool":"2025-08-11 12:48:27 +0000"},"done":true},"minecraft:recipes/decorations/green_carpet":{"criteria":{"has_green_wool":"2025-08-11 12:48:27 +0000"},"done":true},"minecraft:recipes/transportation/mangrove_boat":{"criteria":{"in_water":"2025-08-13 12:25:38 +0000"},"done":true},"minecraft:recipes/transportation/acacia_boat":{"criteria":{"in_water":"2025-08-13 12:25:38 +0000"},"done":true},"minecraft:recipes/transportation/cherry_boat":{"criteria":{"in_water":"2025-08-13 12:25:38 +0000"},"done":true},"minecraft:recipes/transportation/pale_oak_boat":{"criteria":{"in_water":"2025-08-13 12:25:38 +0000"},"done":true},"minecraft:recipes/transportation/bamboo_raft":{"criteria":{"in_water":"2025-08-13 12:25:38 +0000"},"done":true},"minecraft:recipes/transportation/spruce_boat":{"criteria":{"in_water":"2025-08-13 12:25:38 +0000"},"done":true},"minecraft:recipes/transportation/birch_boat":{"criteria":{"in_water":"2025-08-13 12:25:38 +0000"},"done":true},"minecraft:recipes/transportation/oak_boat":{"criteria":{"in_water":"2025-08-13 12:25:38 +0000"},"done":true},"minecraft:recipes/transportation/jungle_boat":{"criteria":{"in_water":"2025-08-13 12:25:38 +0000"},"done":true},"minecraft:recipes/transportation/dark_oak_boat":{"criteria":{"in_water":"2025-08-13 12:25:38 +0000"},"done":true},"minecraft:recipes/tools/flint_and_steel":{"criteria":{"has_obsidian":"2025-08-13 12:26:53 +0000"},"done":true},"minecraft:story/form_obsidian":{"criteria":{"obsidian":"2025-08-13 12:26:53 +0000"},"done":true},"minecraft:recipes/decorations/enchanting_table":{"criteria":{"has_obsidian":"2025-08-13 12:26:53 +0000"},"done":true},"minecraft:recipes/decorations/end_crystal":{"criteria":{"has_ender_eye":"2025-08-13 12:28:09 +0000"},"done":true},"minecraft:recipes/decorations/ender_chest":{"criteria":{"has_ender_eye":"2025-08-13 12:28:09 +0000"},"done":true},"DataVersion":4189}